datasets_dump/__init__.py
datasets_dump/api.py
datasets_dump/cli.py
datasets_dump-0.1.4.dist-info/METADATA
datasets_dump-0.1.4.dist-info/WHEEL
datasets_dump-0.1.4.dist-info/entry_points.txt
datasets_dump-0.1.4.dist-info/licenses/LICENSE
datasets_dump-0.1.4.dist-info/RECORD
