Metadata-Version: 2.3
Name: datasets-dump
Version: 0.1.4
Summary: A tool for dumping datasets from the Hugging Face datasets library
Project-URL: homepage, https://github.com/JacobLinCool/datasets-dump
Project-URL: repository, https://github.com/JacobLinCool/datasets-dump
Author-email: Jacob Lin <jacoblincool@gmail.com>
License: MIT
Keywords: datasets
Requires-Python: >=3.10
Requires-Dist: datasets>=3.1.0
Requires-Dist: numpy
Requires-Dist: pillow
Requires-Dist: soundfile
Requires-Dist: tqdm
